vhlsrs/__init__.py
vhlsrs/__main__.py
vhlsrs/exp_strategy.py
vhlsrs/tmpdir.py
vhlsrs/utils.py
vhlsrs/vivado_exp.py
vhlsrs/vivado_hls_tcl.py
vhlsrs/vivado_report.py
vhlsrs-0.0.95.dist-info/METADATA
vhlsrs-0.0.95.dist-info/WHEEL
vhlsrs-0.0.95.dist-info/top_level.txt
vhlsrs-0.0.95.dist-info/RECORD
