Metadata-Version: 2.1
Name: vhlsrs
Version: 0.0.95
Summary: Package to automate the synthesis of vivado HLS components
Home-page: https://gitlab.inria.fr/lforget/vhls_rs
Author: Luc Forget
Author-email: luc.forget@insa-lyon.fr
License: UNKNOWN
Platform: UNKNOWN
Classifier: Programming Language :: Python :: 3
Classifier: License :: OSI Approved :: MIT License
Classifier: Operating System :: OS Independent
Requires-Python: >=3.6
Requires-Dist: plumbum (>=1.6)
